{
  "main": {
    "id": "d88254efbad07fd8",
    "type": "split",
    "children": [
      {
        "id": "50fa08ad42e27fb6",
        "type": "tabs",
        "children": [
          {
            "id": "eb82426a54972fc1",
            "type": "leaf",
            "state": {
              "type": "markdown",
              "state": {
                "file": "manjaro 安装过程要点记录.md",
                "mode": "source",
                "source": false
              }
            }
          },
          {
            "id": "53b116582e948a39",
            "type": "leaf",
            "state": {
              "type": "markdown",
              "state": {
                "file": "安装alacritty + zsh + oh my zsh + powerlevelk.md",
                "mode": "source",
                "source": false
              }
            }
          },
          {
            "id": "7ccccd56bd33414c",
            "type": "leaf",
            "state": {
              "type": "markdown",
              "state": {
                "file": "安装neovim时.md",
                "mode": "source",
                "source": false
              }
            }
          },
          {
            "id": "0f8f98b4c21e5690",
            "type": "leaf",
            "state": {
              "type": "markdown",
              "state": {
                "file": "manjaro 安装clash.md",
                "mode": "source",
                "source": false
              }
            }
          },
          {
            "id": "3d089499f5d65e37",
            "type": "leaf",
            "state": {
              "type": "markdown",
              "state": {
                "file": "百度网盘.md",
                "mode": "source",
                "source": false
              }
            }
          },
          {
            "id": "85d02137c406a63b",
            "type": "leaf",
            "state": {
              "type": "markdown",
              "state": {
                "file": "manjaro驱动等都正常，就是没有声音.md",
                "mode": "source",
                "source": false
              }
            }
          },
          {
            "id": "c818231ef89d52ef",
            "type": "leaf",
            "state": {
              "type": "markdown",
              "state": {
                "file": "修改默认浏览器.md",
                "mode": "source",
                "source": false
              }
            }
          }
        ],
        "currentTab": 5
      }
    ],
    "direction": "vertical"
  },
  "left": {
    "id": "64b1e7efe7f24a75",
    "type": "split",
    "children": [
      {
        "id": "04636b965f9c8eb9",
        "type": "tabs",
        "children": [
          {
            "id": "25978e4dde03f505",
            "type": "leaf",
            "state": {
              "type": "file-explorer",
              "state": {
                "sortOrder": "alphabetical"
              }
            }
          },
          {
            "id": "bc4bd738a9118c37",
            "type": "leaf",
            "state": {
              "type": "search",
              "state": {
                "query": "",
                "matchingCase": false,
                "explainSearch": false,
                "collapseAll": false,
                "extraContext": false,
                "sortOrder": "alphabetical"
              }
            }
          },
          {
            "id": "b28345ec7a34e117",
            "type": "leaf",
            "state": {
              "type": "starred",
              "state": {}
            }
          }
        ]
      }
    ],
    "direction": "horizontal",
    "width": 300
  },
  "right": {
    "id": "4168b5e00e28461e",
    "type": "split",
    "children": [
      {
        "id": "d6820dc25f01b7ee",
        "type": "tabs",
        "children": [
          {
            "id": "1475d3eacd6dd3d5",
            "type": "leaf",
            "state": {
              "type": "backlink",
              "state": {
                "file": "manjaro驱动等都正常，就是没有声音.md",
                "collapseAll": false,
                "extraContext": false,
                "sortOrder": "alphabetical",
                "showSearch": false,
                "searchQuery": "",
                "backlinkCollapsed": false,
                "unlinkedCollapsed": true
              }
            }
          },
          {
            "id": "bff5e3900eb67b3e",
            "type": "leaf",
            "state": {
              "type": "outgoing-link",
              "state": {
                "file": "manjaro驱动等都正常，就是没有声音.md",
                "linksCollapsed": false,
                "unlinkedCollapsed": true
              }
            }
          },
          {
            "id": "dd97e454251dd46c",
            "type": "leaf",
            "state": {
              "type": "tag",
              "state": {
                "sortOrder": "frequency",
                "useHierarchy": true
              }
            }
          },
          {
            "id": "1ae4fae9b6ed9530",
            "type": "leaf",
            "state": {
              "type": "outline",
              "state": {
                "file": "manjaro驱动等都正常，就是没有声音.md"
              }
            }
          }
        ]
      }
    ],
    "direction": "horizontal",
    "width": 300,
    "collapsed": true
  },
  "active": "85d02137c406a63b",
  "lastOpenFiles": [
    "百度网盘.md",
    "manjaro 安装clash.md",
    "安装neovim时.md",
    "修改默认浏览器.md",
    "deb格式转能够在manjaro安装的格式.md",
    "manjaro 安装过程要点记录.md",
    "README.md",
    "安装alacritty + zsh + oh my zsh + powerlevelk.md",
    "new test.md"
  ]
}